CHANGES.md
LICENSE
MANIFEST.in
README.rst
mdx_collapse.py
setup.py
mdx_collapse.egg-info/PKG-INFO
mdx_collapse.egg-info/SOURCES.txt
mdx_collapse.egg-info/dependency_links.txt
mdx_collapse.egg-info/not-zip-safe
mdx_collapse.egg-info/requires.txt
mdx_collapse.egg-info/top_level.txt