Metadata-Version: 1.1
Name: mdx-collapse
Version: 0.1.0
Summary: A markdown extension for defining collapsible areas
Home-page: https://github.com/AlexJF/mdx_collapse
Author: Alexandre Fonseca
Author-email: alexandrejorgefonseca@gmail.com
License: Apache
Download-URL: https://github.com/AlexJF/mdx_collapse/archive/v0.1.0.zip
Keywords: markdown extension collapse
Platform: UNKNOWN
